more_polars_utils/__init__.py
more_polars_utils/common/__init__.py
more_polars_utils/common/dataframe_assets.py
more_polars_utils/common/dataframe_ext.py
more_polars_utils/common/io/__init__.py
more_polars_utils/common/io/local.py
more_polars_utils/common/io/s3.py
more_polars_utils-0.1.1.dist-info/METADATA
more_polars_utils-0.1.1.dist-info/WHEEL
more_polars_utils-0.1.1.dist-info/RECORD
