Metadata-Version: 2.1
Name: more-polars-utils
Version: 0.1.1
Summary: Utility functions for polars
Author: Kent Czechowski
Author-email: kentcz@hotmail.com
Requires-Python: >=3.8,<4.0
Classifier: Programming Language :: Python :: 3
Classifier: Programming Language :: Python :: 3.8
Classifier: Programming Language :: Python :: 3.9
Classifier: Programming Language :: Python :: 3.10
Classifier: Programming Language :: Python :: 3.11
Classifier: Programming Language :: Python :: 3.12
Requires-Dist: polars (>=0.20.0,<0.21.0)
Requires-Dist: s3fs (>=2024.9.0,<2025.0.0)
